django_asyncapi/__init__.py
django_asyncapi/import_settings.py
django_asyncapi/settings.py
django_asyncapi/static/css/asyncapi_component_1.4.5.css
django_asyncapi/static/css/asyncapi_component_2.1.0.css
django_asyncapi/static/js/asyncapi_component_1.4.5.js
django_asyncapi/static/js/asyncapi_component_2.1.0.js
django_asyncapi/templates/asyncapi.html
django_asyncapi/urls.py
django_asyncapi/utils.py
django_asyncapi/views/__init__.py
django_asyncapi/views/v3/__init__.py
django_asyncapi/views/v3/asyncapi.py
django_asyncapi-0.3.2.dist-info/METADATA
django_asyncapi-0.3.2.dist-info/WHEEL
django_asyncapi-0.3.2.dist-info/RECORD
