Metadata-Version: 2.1
Name: django-asyncapi
Version: 0.3.2
Summary: 
Author: Sergei Konik
Author-email: s.konik.dev@gmail.com
Requires-Python: >=3.10,<4.0
Classifier: Programming Language :: Python :: 3
Classifier: Programming Language :: Python :: 3.10
Classifier: Programming Language :: Python :: 3.11
Classifier: Programming Language :: Python :: 3.12
Requires-Dist: asyncapi-container (==0.4.2)
Requires-Dist: attrs (>=23.2.0,<24.0.0)
Requires-Dist: django (>=3.2.0)
